xk_user/__init__.py
xk_user/user_client.py
xk_user/user_pb2.py
xk_user/user_pb2_grpc.py
xk_user/user_service.py
xk_user-0.0.2.dist-info/METADATA
xk_user-0.0.2.dist-info/WHEEL
xk_user-0.0.2.dist-info/top_level.txt
xk_user-0.0.2.dist-info/RECORD
